odoo/addons/connector_acp_xerox/README.rst
odoo/addons/connector_acp_xerox/__init__.py
odoo/addons/connector_acp_xerox/__manifest__.py
odoo/addons/connector_acp_xerox/data/backend.acp.csv
odoo/addons/connector_acp_xerox/i18n/connector_acp_xerox.pot
odoo/addons/connector_acp_xerox/i18n/es_CL.po
odoo/addons/connector_acp_xerox/models/__init__.py
odoo/addons/connector_acp_xerox/models/backend_acp.py
odoo/addons/connector_acp_xerox/readme/CONFIGURE.rst
odoo/addons/connector_acp_xerox/readme/CONTRIBUTORS.rst
odoo/addons/connector_acp_xerox/readme/DESCRIPTION.rst
odoo/addons/connector_acp_xerox/readme/USAGE.rst
odoo/addons/connector_acp_xerox/static/description/icon.png
odoo/addons/connector_acp_xerox/static/description/index.html
odoo12_addon_connector_acp_xerox-12.0.1.0.0.99.dev5.dist-info/METADATA
odoo12_addon_connector_acp_xerox-12.0.1.0.0.99.dev5.dist-info/WHEEL
odoo12_addon_connector_acp_xerox-12.0.1.0.0.99.dev5.dist-info/top_level.txt
odoo12_addon_connector_acp_xerox-12.0.1.0.0.99.dev5.dist-info/RECORD
